langchain_sqlserver/__init__.py
langchain_sqlserver/py.typed
langchain_sqlserver/vectorstores.py
langchain_sqlserver-0.1.3.dist-info/LICENSE
langchain_sqlserver-0.1.3.dist-info/METADATA
langchain_sqlserver-0.1.3.dist-info/WHEEL
langchain_sqlserver-0.1.3.dist-info/RECORD
