Metadata-Version: 2.3
Name: langchain-sqlserver
Version: 0.1.3
Summary: An integration package to support SQL Server in LangChain.
License: MIT License
Requires-Python: ~=3.9
Classifier: License :: Other/Proprietary License
Classifier: Programming Language :: Python :: 3
Classifier: Programming Language :: Python :: 3.9
Classifier: Programming Language :: Python :: 3.10
Classifier: Programming Language :: Python :: 3.11
Classifier: Programming Language :: Python :: 3.12
Classifier: Programming Language :: Python :: 3.13
Requires-Dist: SQLAlchemy (>=2.0,<3.0)
Requires-Dist: azure-identity (>=1.16,<2.0)
Requires-Dist: langchain-core (>=0.3.0,<0.4.0)
Requires-Dist: numpy (>=1,<3)
Requires-Dist: pyodbc (>=5.0,<6.0)
Project-URL: Repository, https://github.com/langchain-ai/langchain-azure
Project-URL: Release Notes, https://github.com/langchain-ai/langchain-azure/releases
Project-URL: Source Code, https://github.com/langchain-ai/langchain-azure/tree/main/libs/sqlserver
